fhirtools/__init__.py
fhirtools/data_models.py
fhirtools/fhir_client.py
fhirtools/schemas/Account.schema.json
fhirtools/schemas/ActivityDefinition.schema.json
fhirtools/schemas/Address.schema.json
fhirtools/schemas/AdverseEvent.schema.json
fhirtools/schemas/Age.schema.json
fhirtools/schemas/AllergyIntolerance.schema.json
fhirtools/schemas/Annotation.schema.json
fhirtools/schemas/Appointment.schema.json
fhirtools/schemas/AppointmentResponse.schema.json
fhirtools/schemas/Attachment.schema.json
fhirtools/schemas/AuditEvent.schema.json
fhirtools/schemas/BackboneElement.schema.json
fhirtools/schemas/Basic.schema.json
fhirtools/schemas/Binary.schema.json
fhirtools/schemas/BodySite.schema.json
fhirtools/schemas/Bundle.schema.json
fhirtools/schemas/CapabilityStatement.schema.json
fhirtools/schemas/CarePlan.schema.json
fhirtools/schemas/CareTeam.schema.json
fhirtools/schemas/ChargeItem.schema.json
fhirtools/schemas/Claim.schema.json
fhirtools/schemas/ClaimResponse.schema.json
fhirtools/schemas/ClinicalImpression.schema.json
fhirtools/schemas/CodeSystem.schema.json
fhirtools/schemas/CodeableConcept.schema.json
fhirtools/schemas/Coding.schema.json
fhirtools/schemas/Communication.schema.json
fhirtools/schemas/CommunicationRequest.schema.json
fhirtools/schemas/CompartmentDefinition.schema.json
fhirtools/schemas/Composition.schema.json
fhirtools/schemas/ConceptMap.schema.json
fhirtools/schemas/Condition.schema.json
fhirtools/schemas/Consent.schema.json
fhirtools/schemas/ContactDetail.schema.json
fhirtools/schemas/ContactPoint.schema.json
fhirtools/schemas/Contract.schema.json
fhirtools/schemas/Contributor.schema.json
fhirtools/schemas/Count.schema.json
fhirtools/schemas/Coverage.schema.json
fhirtools/schemas/DataElement.schema.json
fhirtools/schemas/DataRequirement.schema.json
fhirtools/schemas/DetectedIssue.schema.json
fhirtools/schemas/Device.schema.json
fhirtools/schemas/DeviceComponent.schema.json
fhirtools-0.0.5.dist-info/METADATA
fhirtools-0.0.5.dist-info/RECORD
fhirtools-0.0.5.dist-info/WHEEL
fhirtools-0.0.5.dist-info/top_level.txt
