Metadata-Version: 2.1
Name: fhirtools
Version: 0.0.5
Summary: FHIR tools for python.
Home-page: https://github.com/jslarraz/fhirtools
Author: Jorge Sancho
Author-email: jslarraz@gmail.com
License: UNKNOWN
Keywords: fhir,development
Platform: UNKNOWN
Requires-Dist: requests (==2.20.0)
Requires-Dist: jsonschema
Requires-Dist: pyOpenSSL (==18.0.0)
